gradio_improvedfileexplorer/__init__.py
gradio_improvedfileexplorer/improvedfileexplorer.py
gradio_improvedfileexplorer/improvedfileexplorer.pyi
gradio_improvedfileexplorer/templates/component/index.js
gradio_improvedfileexplorer/templates/component/style.css
gradio_improvedfileexplorer/templates/example/index.js
gradio_improvedfileexplorer/templates/example/style.css
gradio_improvedfileexplorer-1.0.0.dist-info/METADATA
gradio_improvedfileexplorer-1.0.0.dist-info/WHEEL
gradio_improvedfileexplorer-1.0.0.dist-info/RECORD
