Metadata-Version: 2.4
Name: gradio_improvedfileexplorer
Version: 1.0.0
Summary: Improved UI because it includes breaking changes.
Author-email: Gruny <opiceg@email.cz>
License-Expression: Apache-2.0
Keywords: Easy select only folder,Improved UI,Improved UX,QIM3D,gradio-custom-component,gradio-template-FileExplorer
Classifier: Development Status :: 3 - Alpha
Classifier: Operating System :: OS Independent
Classifier: Programming Language :: Python :: 3
Classifier: Programming Language :: Python :: 3 :: Only
Classifier: Programming Language :: Python :: 3.8
Classifier: Programming Language :: Python :: 3.9
Classifier: Programming Language :: Python :: 3.10
Classifier: Programming Language :: Python :: 3.11
Classifier: Topic :: Scientific/Engineering
Classifier: Topic :: Scientific/Engineering :: Artificial Intelligence
Classifier: Topic :: Scientific/Engineering :: Visualization
Requires-Python: >=3.10
Requires-Dist: gradio<6.0,>=4.0
Provides-Extra: dev
Requires-Dist: build; extra == 'dev'
Requires-Dist: twine; extra == 'dev'
